npack/__init__.py
npack/__main__.py
npack-0.8.0.dist-info/DESCRIPTION.rst
npack-0.8.0.dist-info/METADATA
npack-0.8.0.dist-info/RECORD
npack-0.8.0.dist-info/WHEEL
npack-0.8.0.dist-info/entry_points.txt
npack-0.8.0.dist-info/metadata.json
npack-0.8.0.dist-info/top_level.txt
