Metadata-Version: 2.0
Name: npack
Version: 0.8.0
Summary: Netflix Packager for ContentHub
Home-page: https://contenthub.netflix.com/projects
Author: Anton Margoline
Author-email: amargoline@netflix.com
License: MIT
Download-URL: https://drive.google.com/open?id=0B-J_HAq02T2venZadjRXcDVfajg
Platform: UNKNOWN
Requires-Dist: argparse
Requires-Dist: requests
